tsg/__init__.py
tsg/assets/__init__.py
tsg/assets/background.jpg
tsg/assets/icon.png
tsg/assets/sentences.json
tsg/assets/type-speed.png
tsg-0.1.1.dist-info/METADATA
tsg-0.1.1.dist-info/WHEEL
tsg-0.1.1.dist-info/entry_points.txt
tsg-0.1.1.dist-info/RECORD
