Metadata-Version: 2.1
Name: tsg
Version: 0.1.1
Summary: A Typing Speed Game
License: MIT
Author: Eliaz Bobadilla
Author-email: ultirequiem@pm.me
Requires-Python: >=3.10,<4.0
Classifier: License :: OSI Approved :: MIT License
Classifier: Programming Language :: Python :: 3
Classifier: Programming Language :: Python :: 3.10
Classifier: Programming Language :: Python :: 3.11
Requires-Dist: pygame (>=2.1.2,<3.0.0)
